pyIcarus/__init__.py
pyIcarus/cool_decorators.py
pyIcarus/cool_utils.py
pyIcarus/parsers.py
pyIcarus/replay_pcap.py
pyIcarus/zoomzoom.py
pyIcarus-0.4.20220220155442.dist-info/License
pyIcarus-0.4.20220220155442.dist-info/METADATA
pyIcarus-0.4.20220220155442.dist-info/WHEEL
pyIcarus-0.4.20220220155442.dist-info/top_level.txt
pyIcarus-0.4.20220220155442.dist-info/RECORD
